[{"ar": "\u0645\u0642\u0627\u0644", "en": "p"}, {"ar": "\u0639\u0646\u0648\u0627\u06461", "en": "h1"}, {"ar": "\u0645\u0642\u0627\u0644", "en": "p"}, {"ar": "\u0639\u0646\u0648\u0627\u06461", "en": "h1"}, {"ar": "\u0645\u0642\u0627\u0644", "en": "p"}, {"ar": "\u0639\u0646\u0648\u0627\u06461", "en": "h1"}, {"ar": "\u0645\u0642\u0627\u0644", "en": "p"}, {"ar": "\u0639\u0646\u0648\u0627\u06461", "en": "h1"}, {"en": "a", "ar": "ar"}, {"en": "abbr", "ar": "ar"}, {"en": "acronym", "ar": "ar"}, {"en": "address", "ar": "ar"}, {"en": "applet", "ar": "ar"}, {"en": "area", "ar": "ar"}, {"en": "article", "ar": "ar"}, {"en": "aside", "ar": "ar"}, {"en": "audio", "ar": "ar"}, {"en": "b", "ar": "ar"}, {"en": "base", "ar": "ar"}, {"en": "basefont", "ar": "ar"}, {"en": "bdi", "ar": "ar"}, {"en": "bdo", "ar": "ar"}, {"en": "bgsound", "ar": "ar"}, {"en": "big", "ar": "ar"}, {"en": "blink", "ar": "ar"}, {"en": "blockquote", "ar": "ar"}, {"en": "body", "ar": "ar"}, {"en": "br", "ar": "ar"}, {"en": "button", "ar": "ar"}, {"en": "canvas", "ar": "ar"}, {"en": "caption", "ar": "ar"}, {"en": "center", "ar": "ar"}, {"en": "cite", "ar": "ar"}, {"en": "code", "ar": "ar"}, {"en": "col", "ar": "ar"}, {"en": "colgroup", "ar": "ar"}, {"en": "command", "ar": "ar"}, {"en": "content", "ar": "ar"}, {"en": "contenteditable", "ar": "ar"}, {"en": "data", "ar": "ar"}, {"en": "datalist", "ar": "ar"}, {"en": "dd", "ar": "ar"}, {"en": "del", "ar": "ar"}, {"en": "details", "ar": "ar"}, {"en": "dfn", "ar": "ar"}, {"en": "dialog", "ar": "ar"}, {"en": "dir", "ar": "ar"}, {"en": "div", "ar": "ar"}, {"en": "dl", "ar": "ar"}, {"en": "dt", "ar": "ar"}, {"en": "em", "ar": "ar"}, {"en": "embed", "ar": "ar"}, {"en": "fieldset", "ar": "ar"}, {"en": "figcaption", "ar": "ar"}, {"en": "figure", "ar": "ar"}, {"en": "font", "ar": "ar"}, {"en": "footer", "ar": "ar"}, {"en": "form", "ar": "ar"}, {"en": "frame", "ar": "ar"}, {"en": "frameset", "ar": "ar"}, {"en": "h1", "ar": "ar"}, {"en": "h2", "ar": "\u0639\u0646\u0648\u0627\u06462"}, {"en": "h3", "ar": "ar"}, {"en": "h4", "ar": "ar"}, {"en": "h5", "ar": "ar"}, {"en": "h6", "ar": "ar"}, {"en": "head", "ar": "ar"}, {"en": "header", "ar": "ar"}, {"en": "hgroup", "ar": "ar"}, {"en": "hr", "ar": "ar"}, {"en": "html", "ar": "ar"}, {"en": "i", "ar": "ar"}, {"en": "iframe", "ar": "ar"}, {"en": "image", "ar": "ar"}, {"en": "img", "ar": "ar"}, {"en": "input", "ar": "ar"}, {"en": "ins", "ar": "ar"}, {"en": "kbd", "ar": "ar"}, {"en": "keygen", "ar": "ar"}, {"en": "label", "ar": "ar"}, {"en": "legend", "ar": "ar"}, {"en": "li", "ar": "ar"}, {"en": "link", "ar": "ar"}, {"en": "main", "ar": "ar"}, {"en": "map", "ar": "ar"}, {"en": "mark", "ar": "ar"}, {"en": "marquee", "ar": "ar"}, {"en": "math", "ar": "ar"}, {"en": "menu", "ar": "ar"}, {"en": "menuitem", "ar": "ar"}, {"en": "meta", "ar": "ar"}, {"en": "meter", "ar": "ar"}, {"en": "nav", "ar": "ar"}, {"en": "nobr", "ar": "ar"}, {"en": "noembed", "ar": "ar"}, {"en": "noframes", "ar": "ar"}, {"en": "noscript", "ar": "ar"}, {"en": "object", "ar": "ar"}, {"en": "ol", "ar": "ar"}, {"en": "optgroup", "ar": "ar"}, {"en": "option", "ar": "ar"}, {"en": "output", "ar": "ar"}, {"en": "p", "ar": "ar"}, {"en": "param", "ar": "ar"}, {"en": "picture", "ar": "ar"}, {"en": "plaintext", "ar": "ar"}, {"en": "portal", "ar": "ar"}, {"en": "pre", "ar": "ar"}, {"en": "progress", "ar": "ar"}, {"en": "q", "ar": "ar"}, {"en": "rb", "ar": "ar"}, {"en": "rp", "ar": "ar"}, {"en": "rt", "ar": "ar"}, {"en": "rtc", "ar": "ar"}, {"en": "ruby", "ar": "ar"}, {"en": "s", "ar": "ar"}, {"en": "samp", "ar": "ar"}, {"en": "script", "ar": "ar"}, {"en": "section", "ar": "ar"}, {"en": "select", "ar": "ar"}, {"en": "shadow", "ar": "ar"}, {"en": "slot", "ar": "ar"}, {"en": "small", "ar": "ar"}, {"en": "source", "ar": "ar"}, {"en": "spacer", "ar": "ar"}, {"en": "span", "ar": "ar"}, {"en": "strike", "ar": "ar"}, {"en": "strong", "ar": "ar"}, {"en": "style", "ar": "ar"}, {"en": "sub", "ar": "ar"}, {"en": "summary", "ar": "ar"}, {"en": "sup", "ar": "ar"}, {"en": "svg", "ar": "ar"}, {"en": "table", "ar": "ar"}, {"en": "tbody", "ar": "ar"}, {"en": "td", "ar": "ar"}, {"en": "template", "ar": "ar"}, {"en": "textarea", "ar": "ar"}, {"en": "tfoot", "ar": "ar"}, {"en": "th", "ar": "ar"}, {"en": "thead", "ar": "ar"}, {"en": "time", "ar": "ar"}, {"en": "title", "ar": "ar"}, {"en": "tr", "ar": "ar"}, {"en": "track", "ar": "ar"}, {"en": "tt", "ar": "ar"}, {"en": "u", "ar": "ar"}, {"en": "ul", "ar": "ar"}, {"en": "var", "ar": "ar"}, {"en": "video", "ar": "ar"}, {"en": "wbr", "ar": "ar"}, {"en": "xmp", "ar": "ar"}]